hutch_python/__init__.py
hutch_python/__main__.py
hutch_python/_version.py
hutch_python/bug.py
hutch_python/cache.py
hutch_python/calc_defaults.py
hutch_python/cam_load.py
hutch_python/cli.py
hutch_python/constants.py
hutch_python/debug.py
hutch_python/env_version.py
hutch_python/epics_arch.py
hutch_python/exp_load.py
hutch_python/happi.py
hutch_python/ipython_log.py
hutch_python/ipython_session_timer.py
hutch_python/lcls.py
hutch_python/load_conf.py
hutch_python/log_setup.py
hutch_python/logging.yml
hutch_python/mpl_config.py
hutch_python/namespace.py
hutch_python/obj_config.py
hutch_python/ophyd_settings.py
hutch_python/options.py
hutch_python/plan_defaults.py
hutch_python/plan_wrappers.py
hutch_python/print_hint_banner.py
hutch_python/pt_app_config.py
hutch_python/qs_load.py
hutch_python/sim.py
hutch_python/startup_script.py
hutch_python/user_load.py
hutch_python/utils.py
hutch_python/version.py
hutch_python/cookiecutter/cookiecutter.json
hutch_python/cookiecutter/{{ cookiecutter.hutch }}/.gitignore
hutch_python/cookiecutter/{{ cookiecutter.hutch }}/README.md
hutch_python/cookiecutter/{{ cookiecutter.hutch }}/conf.yml
hutch_python/cookiecutter/{{ cookiecutter.hutch }}/set-dev
hutch_python/cookiecutter/{{ cookiecutter.hutch }}/{{ cookiecutter.hutch }}env
hutch_python/cookiecutter/{{ cookiecutter.hutch }}/{{ cookiecutter.hutch }}python
hutch_python/cookiecutter/{{ cookiecutter.hutch }}/experiments/__init__.py
hutch_python/cookiecutter/{{ cookiecutter.hutch }}/{{ cookiecutter.hutch }}/__init__.py
hutch_python/cookiecutter/{{ cookiecutter.hutch }}/{{ cookiecutter.hutch }}/beamline.py
hutch_python/templates/issue.template
hutch_python/tests/__init__.py
hutch_python/tests/bad_script.py
hutch_python/tests/camviewer.cfg
hutch_python/tests/conf.yaml
hutch_python/tests/conftest.py
hutch_python/tests/happi_db.json
hutch_python/tests/sample_module_1.py
hutch_python/tests/sample_module_2.py
hutch_python/tests/script.py
hutch_python/tests/test_bug.py
hutch_python-1.23.1.dist-info/licenses/AUTHORS.rst
hutch_python-1.23.1.dist-info/licenses/LICENSE
hutch_python-1.23.1.dist-info/METADATA
hutch_python-1.23.1.dist-info/WHEEL
hutch_python-1.23.1.dist-info/entry_points.txt
hutch_python-1.23.1.dist-info/top_level.txt
hutch_python-1.23.1.dist-info/RECORD
