Metadata-Version: 2.4
Name: hutch-python
Version: 1.23.1
Summary: Launcher and Config Reader for LCLS Interactive IPython Sessions
Author: SLAC National Accelerator Laboratory
License: Copyright (c) 2023, The Board of Trustees of the Leland Stanford Junior
Classifier: Development Status :: 5 - Production/Stable
Classifier: Natural Language :: English
Classifier: Programming Language :: Python :: 3
Requires-Python: >=3.9
License-File: LICENSE
License-File: AUTHORS.rst
Requires-Dist: archapp>=1.0.2
Requires-Dist: bluesky>=1.8.0
Requires-Dist: coloredlogs>=15.0.0
Requires-Dist: cookiecutter>=1.7.0
Requires-Dist: happi>=1.9.0
Requires-Dist: ipython<9.0.0
Requires-Dist: jinja2>=2.11.0
Requires-Dist: lightpath>=1.0.1
Requires-Dist: matplotlib>=3.4.0
Requires-Dist: nabs>=1.5.0
Requires-Dist: pcdscalc>=0.6.0
Requires-Dist: pcdsdaq>=2.3.0
Requires-Dist: pcdsdevices>8.7.0
Requires-Dist: pcdsutils>=0.5.0
Requires-Dist: psdaq-control-minimal
Requires-Dist: pyfiglet>=0.8.0
Requires-Dist: pykerberos
Requires-Dist: pyqt5
Requires-Dist: pyyaml>=5.4.0
Requires-Dist: requests>=2.26.0
Requires-Dist: simplejson>=3.17.0
Provides-Extra: test
Requires-Dist: lightpath; extra == "test"
Requires-Dist: packaging; extra == "test"
Requires-Dist: pytest; extra == "test"
Requires-Dist: pytest-timeout; extra == "test"
Provides-Extra: doc
Requires-Dist: docs-versions-menu; extra == "doc"
Requires-Dist: nbsphinx; extra == "doc"
Requires-Dist: sphinx; extra == "doc"
Requires-Dist: sphinx_rtd_theme; extra == "doc"
Requires-Dist: sphinxcontrib-jquery; extra == "doc"
Requires-Dist: pypandoc; extra == "doc"
Dynamic: license-file
